kastely/__init__.py
kastely/__main__.py
kastely/interface.py
kastely/roll.py
kastely/start.py
kastely-0.1.8.dist-info/entry_points.txt
kastely-0.1.8.dist-info/WHEEL
kastely-0.1.8.dist-info/METADATA
kastely-0.1.8.dist-info/RECORD
