Metadata-Version: 2.1
Name: kastely
Version: 0.1.8
Summary: 🏰 Race to the castle with this fun CLI Board Game!
Author: Sam Poder
Author-email: hi@sampoder.com
Requires-Python: >=3.7,<4.0
Classifier: Programming Language :: Python :: 3
Classifier: Programming Language :: Python :: 3.7
Requires-Dist: Unidecode (>=1.1,<2.0)
Requires-Dist: ascii (>=3.6,<4.0)
Requires-Dist: colorama (>=0.4.3,<0.5.0)
Requires-Dist: pyfiglet (>=0.8.0,<0.9.0)
Requires-Dist: tabulate (>=0.8.7,<0.9.0)
